PyQtGuiLib/__init__.py
PyQtGuiLib/animation/PropertyAnimation.py
PyQtGuiLib/animation/__init__.py
PyQtGuiLib/animation/animation.py
PyQtGuiLib/core/__init__.py
PyQtGuiLib/core/bubbleWidget.py
PyQtGuiLib/core/slideShow.py
PyQtGuiLib/core/layout/__init__.py
PyQtGuiLib/core/layout/flowLayout.py
PyQtGuiLib/core/palettes/__init__.py
PyQtGuiLib/core/palettes/colorHsv.py
PyQtGuiLib/core/palettes/paletteFrame.py
PyQtGuiLib/core/palettes/palettetools.py
PyQtGuiLib/core/palettes/paletteTools/__init__.py
PyQtGuiLib/core/palettes/paletteTools/area.py
PyQtGuiLib/core/palettes/paletteTools/paletteToolUI.py
PyQtGuiLib/core/palettes/paletteTools/palettetools.py
PyQtGuiLib/core/progressBar/__init__.py
PyQtGuiLib/core/progressBar/gradientBar.py
PyQtGuiLib/core/switchButtons/__init__.py
PyQtGuiLib/core/switchButtons/swButton.py
PyQtGuiLib/decorator/__init__.py
PyQtGuiLib/decorator/designer.py
PyQtGuiLib/header/__init__.py
PyQtGuiLib/header/error.py
PyQtGuiLib/header/utility.py
PyQtGuiLib/header/versions.py
PyQtGuiLib/header/Qt/__init__.py
PyQtGuiLib/header/Qt/qt.py
PyQtGuiLib/header/Qt/qtBluetooth.py
PyQtGuiLib/header/Qt/qtCharts.py
PyQtGuiLib/header/Qt/qtConcurrent.py
PyQtGuiLib/header/Qt/qtCore.py
PyQtGuiLib/header/Qt/qtDataVisualization.py
PyQtGuiLib/header/Qt/qtGui.py
PyQtGuiLib/header/Qt/qtHelp.py
PyQtGuiLib/header/Qt/qtMultimedia.py
PyQtGuiLib/header/Qt/qtMultimediaWidgets.py
PyQtGuiLib/header/Qt/qtNetwork.py
PyQtGuiLib/header/Qt/qtNetworkAuth.py
PyQtGuiLib/header/Qt/qtSip.py
PyQtGuiLib/header/Qt/qtSvg.py
PyQtGuiLib/header/Qt/qtUic.py
PyQtGuiLib/header/Qt/qtWidgets.py
PyQtGuiLib/header/py/__init__.py
PyQtGuiLib/header/py/common.py
PyQtGuiLib/styles/__init__.py
PyQtGuiLib/styles/styleAnalysis.py
PyQtGuiLib/styles/superPainter/__init__.py
PyQtGuiLib/styles/superPainter/superPainter.py
test/__init__.py
test/test1.py
test/test_BubbleWidget.py
test/test_PaletteTools.py
test/test_gradientBar.py
test/test_switchButton.py
test/test_Animation/1.py
test/test_Animation/__init__.py
PyQtGuiLib_PySide-1.3.dist-info/LICENSE.txt
PyQtGuiLib_PySide-1.3.dist-info/METADATA
PyQtGuiLib_PySide-1.3.dist-info/WHEEL
PyQtGuiLib_PySide-1.3.dist-info/top_level.txt
PyQtGuiLib_PySide-1.3.dist-info/RECORD
