Metadata-Version: 2.1
Name: PyQtGuiLib-PySide
Version: 1.3
Summary: Python version of the qt component library.
Home-page: https://github.com/LX-sys/PyQtGuiLib-PySide
Author: LX
Author-email: lx984608061@163.com
License: GPL
Classifier: Programming Language :: Python :: 3.6
Classifier: Programming Language :: Python :: 3.7
Classifier: Programming Language :: Python :: 3.8
Classifier: Programming Language :: Python :: 3.9
Classifier: License :: OSI Approved :: GNU General Public License v3 or later (GPLv3+)
Classifier: Operating System :: OS Independent
License-File: LICENSE.txt
